{"FullPath":"H:\\Ragrug\\ragrug\\arclient\\unity\\June Build\\RR-vu\\Vizario.CoreBridgeSink.winmd","InProcServers":{},"Namespaces":{"Vizario.CoreBridgeSink.CoreBridgeMediaSinkProxy":"Vizario.CoreBridgeSink","Vizario.CoreBridgeSink.RawImageCapturedArgs":"Vizario.CoreBridgeSink","Vizario.CoreBridgeSink.__IRawImageCapturedArgsPublicNonVirtuals":"Vizario.CoreBridgeSink","Vizario.CoreBridgeSink.__ICoreBridgeMediaSinkProxyPublicNonVirtuals":"Vizario.CoreBridgeSink","Vizario.CoreBridgeSink.__ICoreBridgeMediaSinkProxyProtectedNonVirtuals":"Vizario.CoreBridgeSink"},"RootNamespace":"Vizario.CoreBridgeSink","AssemblyVersion":"16.0.29311.281"}